CHANGES.txt
MANIFEST.in
README.rst
setup.cfg
setup.py
src/procyon/__init__.py
src/procyon/panels.py
src/procyon.egg-info/PKG-INFO
src/procyon.egg-info/SOURCES.txt
src/procyon.egg-info/dependency_links.txt
src/procyon.egg-info/not-zip-safe
src/procyon.egg-info/requires.txt
src/procyon.egg-info/top_level.txt
src/procyon/base/__init__.py
src/procyon/base/event.py
src/procyon/base/interfaces.py
src/procyon/base/model.py
src/procyon/base/panels.py
src/procyon/templates/panels/flash.jinja2
src/procyon/templates/panels/login_menuitem.jinja2
src/procyon/user/__init__.py
src/procyon/user/api.py
src/procyon/user/directives.py
src/procyon/user/event.py
src/procyon/user/interfaces.py
src/procyon/user/model.py
src/procyon/user/panels.py
src/procyon/user/views.py