Metadata-Version: 1.1
Name: procyon
Version: 0.1
Summary: procyon is a collection of reusable components for Pyramid
Home-page: http://procyon.readthedocs.org/en/latest/
Author: Nozomu Kaneko
Author-email: nozom.kaneko@gmail.com
License: UNKNOWN
Keywords: web pyramid pylons
Platform: UNKNOWN
Classifier: Programming Language :: Python
Classifier: Framework :: Pyramid
Classifier: Topic :: Internet :: WWW/HTTP
Classifier: Topic :: Internet :: WWW/HTTP :: WSGI :: Application
